finesse_benchmark/__init__.py
finesse_benchmark/benchmark.default.yaml
finesse_benchmark/benchmark.leaderboard.yaml
finesse_benchmark/benchmark.scaffold.py
finesse_benchmark/cli.py
finesse_benchmark/config.py
finesse_benchmark/evaluator.py
finesse_benchmark/implementations.py
finesse_benchmark/inspect.py
finesse_benchmark/interfaces.py
finesse_benchmark/runner.py
finesse_benchmark/scoring.py
finesse_benchmark/utils.py
finesse_benchmark-0.14.0.dist-info/entry_points.txt
finesse_benchmark-0.14.0.dist-info/licenses/licence
finesse_benchmark-0.14.0.dist-info/METADATA
finesse_benchmark-0.14.0.dist-info/WHEEL
finesse_benchmark-0.14.0.dist-info/RECORD
