Metadata-Version: 2.4
Name: finesse-benchmark
Version: 0.14.0
Summary: sophisticated evaluation framework designed to assess the performance of long-context embedding models on semantic understanding and information retention
License-File: licence
Author: winter.sci.dev
Author-email: enzoescipy@gmail.com
Requires-Python: >=3.10,<3.14
Classifier: Programming Language :: Python :: 3
Classifier: Programming Language :: Python :: 3.10
Classifier: Programming Language :: Python :: 3.11
Classifier: Programming Language :: Python :: 3.12
Classifier: Programming Language :: Python :: 3.13
Requires-Dist: datasets (>=4.0.0,<4.1.0)
Requires-Dist: einops (>=0.8.1,<0.9.0)
Requires-Dist: litellm (>=1.78.0,<1.79.0)
Requires-Dist: matplotlib (>=3.10.0,<3.11.0)
Requires-Dist: py-cpuinfo (>=9.0.0,<9.1.0)
Requires-Dist: pyarrow (>=18.1.0,<18.2.0)
Requires-Dist: pydantic (>=2.11.0,<2.12.0)
Requires-Dist: ruamel.yaml (>=0.18,<1.0)
Requires-Dist: seaborn (>=0.13.0,<0.14.0)
Requires-Dist: tiktoken (>=0.12.0,<0.13.0)
Requires-Dist: torch (==2.8.0)
Requires-Dist: transformers (>=4.57.0,<4.58.0)
Requires-Dist: typer (>=0.20.0,<0.21.0)
